<?xml version="1.0" encoding="UTF-8"?>
<page pageId="Page41" pageName="Release Notes" title="">
    <abstract></abstract>
    <keywords></keywords>
    <contents>
        <line Align="Left">
            <content style="Normal">Network Mom Availability Release History:</content>
        </line>
        <list ListStyle="listDisc">
            <listItem style="Normal">
                <line Align="Left">
                    <content style="Normal">Version 1.0: February 2019: Initial release</content>
                </line>
            </listItem>
            <listItem style="Normal">
                <line Align="Left">
                    <content style="Normal">Version 1.1: February 2019: Cosmetic and documentation updates</content>
                </line>
            </listItem>
        </list>
    </contents>
</page>